Metadata-Version: 2.1
Name: macrbxmonitor
Version: 0.0.1.dev1
Summary: A simple script that monitors roblox asynchronously without modifying and reading the game's client. This only works in MacOS
Home-page: https://github.com/helloplauz10/rbxmonitormac/
Author: cuteuwu
License: MIT License
Classifier: Operating System :: MacOS :: MacOS X
Classifier: Programming Language :: Python
Requires-Dist: psutil
